anansi_sdk/__init__.py
anansi_sdk/api_client.py
anansi_sdk/configuration.py
anansi_sdk/rest.py
anansi_sdk/api/__init__.py
anansi_sdk/api/default_api.py
anansi_sdk/models/__init__.py
anansi_sdk/models/embedding_request.py
anansi_sdk/models/error_response.py
anansi_sdk/models/genai_info.py
anansi_sdk/models/graph_request.py
anansi_sdk/models/graph_request_item.py
anansi_sdk/models/graph_request_item_node_id_info.py
anansi_sdk/models/graph_response.py
anansi_sdk/models/one_of_graph_response_edges.py
anansi_sdk/models/one_of_graph_response_nodes.py
anansi_sdk/models/relationship.py
anansi_sdk/models/relationship_unused_parameter_body.py
anansi_sdk/models/success_response_on_crud.py
anansi_sdk-1.2.1.dist-info/licenses/LICENSE
test/__init__.py
test/test_default_api.py
test/test_error_response.py
test/test_graph_request.py
test/test_graph_request_item.py
test/test_graph_request_item_node_id_info.py
test/test_graph_response.py
test/test_one_of_graph_response_edges.py
test/test_one_of_graph_response_nodes.py
test/test_relationship.py
test/test_relationship_unused_parameter_body.py
test/test_success_response_on_crud.py
anansi_sdk-1.2.1.dist-info/METADATA
anansi_sdk-1.2.1.dist-info/WHEEL
anansi_sdk-1.2.1.dist-info/top_level.txt
anansi_sdk-1.2.1.dist-info/RECORD
