Metadata-Version: 2.4
Name: anansi-sdk
Version: 1.2.1
Summary: Anansi REST API
Home-page: https://www.anansihub.com/
Author-email: admin@suketa.in
Keywords: Swagger,Anansi REST API,Anansi SDK
License-File: LICENSE
Requires-Dist: urllib3>=1.15
Requires-Dist: six>=1.10
Requires-Dist: certifi
Requires-Dist: python-dateutil
Dynamic: author-email
Dynamic: description
Dynamic: description-content-type
Dynamic: home-page
Dynamic: keywords
Dynamic: license-file
Dynamic: requires-dist
Dynamic: summary
